ext/snake/__init__.py
ext/snake/py.typed
_ext-snake.pth
ext_snake-1.0.0.dist-info/METADATA
ext_snake-1.0.0.dist-info/WHEEL
ext_snake-1.0.0.dist-info/RECORD
