Metadata-Version: 2.4
Name: ext-snake
Version: 1.0.0
Summary: Add '.🐍' possible extensions.
Author-email: Andrew Hoekstra <andrew@pointevector.com>
License-Expression: MIT
Classifier: Development Status :: 5 - Production/Stable
Classifier: Intended Audience :: Developers
Classifier: License :: OSI Approved :: MIT License
Classifier: Programming Language :: Python :: 3
Requires-Python: >=3.3
